sixfour.py
sixfour-1.3.3.data/scripts/sixfour
sixfour-1.3.3.dist-info/DESCRIPTION.rst
sixfour-1.3.3.dist-info/METADATA
sixfour-1.3.3.dist-info/pydist.json
sixfour-1.3.3.dist-info/RECORD
sixfour-1.3.3.dist-info/top_level.txt
sixfour-1.3.3.dist-info/WHEEL
